AgentService/__init__.py
AgentService/agent/__init__.py
AgentService/agent/agent.py
AgentService/agent/tool.py
AgentService/app/__init__.py
AgentService/app/app.py
AgentService/app/routes/__init__.py
AgentService/app/routes/chat/__init__.py
AgentService/app/routes/chat/chat.py
AgentService/app/routes/chat/models.py
AgentService/app/routes/meta/__init__.py
AgentService/app/routes/meta/meta.py
AgentService/app/routes/meta/models.py
AgentService/app/routes/storage/__init__.py
AgentService/app/routes/storage/models.py
AgentService/app/routes/storage/storage.py
AgentService/cli/__init__.py
AgentService/cli/create.py
AgentService/cli/create_nocode.py
AgentService/cli/image.py
AgentService/cli/start.py
AgentService/cli/start_nocode.py
AgentService/cli/tool.py
AgentService/config/__init__.py
AgentService/config/config.py
AgentService/connector/__init__.py
AgentService/connector/connector.py
AgentService/connector/event.py
AgentService/connector/models/__init__.py
AgentService/connector/models/models.py
AgentService/connector/types/__init__.py
AgentService/connector/types/agent.py
AgentService/connector/types/chat.py
AgentService/connector/types/message.py
AgentService/connector/types/meta.py
AgentService/connector/types/storage.py
AgentService/connector/types/tool.py
AgentService/enums/__init__.py
AgentService/enums/agent.py
AgentService/enums/chat.py
AgentService/enums/message.py
AgentService/enums/response.py
AgentService/enums/tool.py
AgentService/templates/agent-image/Dockerfile.tmpl
AgentService/templates/project/agent.cfg
AgentService/templates/project/manage.py
AgentService/templates/project/requirements.txt
AgentService/templates/project/agent/__init__.py
AgentService/templates/project/agent/agent.py
AgentService/templates/project/resources/logs/default
AgentService/templates/project/tools/__init__.py
AgentService/templates/project_nocode/agent.cfg
AgentService/templates/project_nocode/agent.json
AgentService/templates/project_nocode/manage.py
agentservice-0.0.144.dist-info/licenses/LICENSE.txt
agentservice-0.0.144.dist-info/METADATA
agentservice-0.0.144.dist-info/WHEEL
agentservice-0.0.144.dist-info/entry_points.txt
agentservice-0.0.144.dist-info/top_level.txt
agentservice-0.0.144.dist-info/RECORD
