Metadata-Version: 2.4
Name: AgentService
Version: 0.0.144
Summary: AgentService
Author-email: Denis Minka <minka.denis@gmail.com>
License-File: LICENSE.txt
Requires-Dist: click
Requires-Dist: fastapi
Requires-Dist: pydantic
Requires-Dist: motor
Requires-Dist: openai==1.107.0
Requires-Dist: uvicorn
Requires-Dist: loguru
Requires-Dist: aiohttp
Requires-Dist: beanie
Dynamic: license-file
